didyoumean_nhannht/__init__.py
didyoumean_nhannht/__main__.py
didyoumean_nhannht/main.py
didyoumean_nhannht-0.1.15.dist-info/entry_points.txt
didyoumean_nhannht-0.1.15.dist-info/WHEEL
didyoumean_nhannht-0.1.15.dist-info/METADATA
didyoumean_nhannht-0.1.15.dist-info/RECORD
