Metadata-Version: 2.1
Name: didyoumean-nhannht
Version: 0.1.15
Summary: 
Author: nhanclassroom
Author-email: nhanclassroom@gmail.com
Requires-Python: >=3.10,<4.0
Classifier: Programming Language :: Python :: 3
Classifier: Programming Language :: Python :: 3.10
Classifier: Programming Language :: Python :: 3.11
Requires-Dist: click (>=8.1.3,<9.0.0)
